{
  "last_node_id": 14,
  "last_link_id": 16,
  "nodes": [
    {
      "id": 99,
      "type": "Note",
      "pos": [40, 20],
      "size": [900, 70],
      "flags": {},
      "order": 0,
      "mode": 0,
      "inputs": [],
      "outputs": [],
      "properties": {},
      "widgets_values": ["IP-ADAPTER + LoRA STACK\nLoad a reference photo of her face into the Load Image node. The LoRA + IP-Adapter combine for tight identity binding.\nFor 4GB VRAM: launch ComfyUI with --lowvram. Resolution is 768x1024 to fit. Slow but works."],
      "color": "#222",
      "bgcolor": "#444"
    },
    {
      "id": 1,
      "type": "CheckpointLoaderSimple",
      "pos": [40, 120],
      "size": [340, 100],
      "flags": {},
      "order": 1,
      "mode": 0,
      "inputs": [],
      "outputs": [
        {"name": "MODEL", "type": "MODEL", "links": [1], "slot_index": 0},
        {"name": "CLIP", "type": "CLIP", "links": [2], "slot_index": 1},
        {"name": "VAE", "type": "VAE", "links": [3], "slot_index": 2}
      ],
      "properties": {"Node name for S&R": "CheckpointLoaderSimple"},
      "widgets_values": ["Juggernaut-XL_v9.safetensors"]
    },
    {
      "id": 2,
      "type": "LoraLoader",
      "pos": [410, 120],
      "size": [340, 130],
      "flags": {},
      "order": 2,
      "mode": 0,
      "inputs": [
        {"name": "model", "type": "MODEL", "link": 1},
        {"name": "clip", "type": "CLIP", "link": 2}
      ],
      "outputs": [
        {"name": "MODEL", "type": "MODEL", "links": [4], "slot_index": 0},
        {"name": "CLIP", "type": "CLIP", "links": [5, 6], "slot_index": 1}
      ],
      "properties": {"Node name for S&R": "LoraLoader"},
      "widgets_values": ["sks_woman_lora_v3.safetensors", 0.75, 0.75]
    },
    {
      "id": 3,
      "type": "IPAdapterUnifiedLoader",
      "pos": [780, 120],
      "size": [340, 110],
      "flags": {},
      "order": 3,
      "mode": 0,
      "inputs": [
        {"name": "model", "type": "MODEL", "link": 4}
      ],
      "outputs": [
        {"name": "model", "type": "MODEL", "links": [7], "slot_index": 0},
        {"name": "ipadapter", "type": "IPADAPTER", "links": [8], "slot_index": 1}
      ],
      "properties": {"Node name for S&R": "IPAdapterUnifiedLoader"},
      "widgets_values": ["PLUS FACE (portraits)"]
    },
    {
      "id": 4,
      "type": "LoadImage",
      "pos": [780, 280],
      "size": [340, 320],
      "flags": {},
      "order": 4,
      "mode": 0,
      "inputs": [],
      "outputs": [
        {"name": "IMAGE", "type": "IMAGE", "links": [9], "slot_index": 0},
        {"name": "MASK", "type": "MASK", "links": null, "slot_index": 1}
      ],
      "properties": {"Node name for S&R": "LoadImage"},
      "widgets_values": ["photo_03.jpg", "image"]
    },
    {
      "id": 5,
      "type": "IPAdapterAdvanced",
      "pos": [1150, 120],
      "size": [340, 270],
      "flags": {},
      "order": 5,
      "mode": 0,
      "inputs": [
        {"name": "model", "type": "MODEL", "link": 7},
        {"name": "ipadapter", "type": "IPADAPTER", "link": 8},
        {"name": "image", "type": "IMAGE", "link": 9},
        {"name": "image_negative", "type": "IMAGE", "link": null},
        {"name": "attn_mask", "type": "MASK", "link": null},
        {"name": "clip_vision", "type": "CLIP_VISION", "link": null}
      ],
      "outputs": [
        {"name": "MODEL", "type": "MODEL", "links": [10], "slot_index": 0}
      ],
      "properties": {"Node name for S&R": "IPAdapterAdvanced"},
      "widgets_values": [0.6, 0.0, 1.0, "standard", "concat", "V only"]
    },
    {
      "id": 6,
      "type": "CLIPTextEncode",
      "pos": [40, 280],
      "size": [340, 180],
      "flags": {},
      "order": 6,
      "mode": 0,
      "inputs": [
        {"name": "clip", "type": "CLIP", "link": 5}
      ],
      "outputs": [
        {"name": "CONDITIONING", "type": "CONDITIONING", "links": [11], "slot_index": 0}
      ],
      "properties": {"Node name for S&R": "CLIPTextEncode"},
      "widgets_values": ["sks_woman, woman, golden hour, sun-drenched park, cinematic portrait, photographic"],
      "color": "#232",
      "bgcolor": "#353"
    },
    {
      "id": 7,
      "type": "CLIPTextEncode",
      "pos": [40, 490],
      "size": [340, 180],
      "flags": {},
      "order": 7,
      "mode": 0,
      "inputs": [
        {"name": "clip", "type": "CLIP", "link": 6}
      ],
      "outputs": [
        {"name": "CONDITIONING", "type": "CONDITIONING", "links": [12], "slot_index": 0}
      ],
      "properties": {"Node name for S&R": "CLIPTextEncode"},
      "widgets_values": ["blurry, deformed, ugly, bad anatomy, low quality, plastic skin, stray hairs, peach fuzz, oversharpened, cartoon, anime, 3d render, blonde hair, green eyes, watermark"],
      "color": "#322",
      "bgcolor": "#533"
    },
    {
      "id": 8,
      "type": "EmptyLatentImage",
      "pos": [410, 280],
      "size": [340, 110],
      "flags": {},
      "order": 8,
      "mode": 0,
      "inputs": [],
      "outputs": [
        {"name": "LATENT", "type": "LATENT", "links": [13], "slot_index": 0}
      ],
      "properties": {"Node name for S&R": "EmptyLatentImage"},
      "widgets_values": [768, 1024, 1]
    },
    {
      "id": 9,
      "type": "KSampler",
      "pos": [1520, 120],
      "size": [320, 280],
      "flags": {},
      "order": 9,
      "mode": 0,
      "inputs": [
        {"name": "model", "type": "MODEL", "link": 10},
        {"name": "positive", "type": "CONDITIONING", "link": 11},
        {"name": "negative", "type": "CONDITIONING", "link": 12},
        {"name": "latent_image", "type": "LATENT", "link": 13}
      ],
      "outputs": [
        {"name": "LATENT", "type": "LATENT", "links": [14], "slot_index": 0}
      ],
      "properties": {"Node name for S&R": "KSampler"},
      "widgets_values": [42, "fixed", 30, 5.5, "dpmpp_2m", "karras", 1]
    },
    {
      "id": 10,
      "type": "VAEDecode",
      "pos": [1870, 120],
      "size": [200, 50],
      "flags": {},
      "order": 10,
      "mode": 0,
      "inputs": [
        {"name": "samples", "type": "LATENT", "link": 14},
        {"name": "vae", "type": "VAE", "link": 3}
      ],
      "outputs": [
        {"name": "IMAGE", "type": "IMAGE", "links": [15], "slot_index": 0}
      ],
      "properties": {"Node name for S&R": "VAEDecode"},
      "widgets_values": []
    },
    {
      "id": 11,
      "type": "SaveImage",
      "pos": [1870, 200],
      "size": [340, 270],
      "flags": {},
      "order": 11,
      "mode": 0,
      "inputs": [
        {"name": "images", "type": "IMAGE", "link": 15}
      ],
      "outputs": [],
      "properties": {"Node name for S&R": "SaveImage"},
      "widgets_values": ["sks_woman_ipadapter"]
    }
  ],
  "links": [
    [1,  1, 0, 2, 0, "MODEL"],
    [2,  1, 1, 2, 1, "CLIP"],
    [3,  1, 2, 10, 1, "VAE"],
    [4,  2, 0, 3, 0, "MODEL"],
    [5,  2, 1, 6, 0, "CLIP"],
    [6,  2, 1, 7, 0, "CLIP"],
    [7,  3, 0, 5, 0, "MODEL"],
    [8,  3, 1, 5, 1, "IPADAPTER"],
    [9,  4, 0, 5, 2, "IMAGE"],
    [10, 5, 0, 9, 0, "MODEL"],
    [11, 6, 0, 9, 1, "CONDITIONING"],
    [12, 7, 0, 9, 2, "CONDITIONING"],
    [13, 8, 0, 9, 3, "LATENT"],
    [14, 9, 0, 10, 0, "LATENT"],
    [15, 10, 0, 11, 0, "IMAGE"]
  ],
  "groups": [],
  "config": {},
  "extra": {"ds": {"scale": 0.7, "offset": [0, 0]}},
  "version": 0.4
}
